<?xml version="1.0" encoding="utf-8" ?><dwsync><file name="Thumbs.db" server="ftp.gfjourney.com/public_html/" local="3500762112" remote="318763443894731472" Dst="-1" /><file name="St.Law.jpg" server="ftp.gfjourney.com/public_html/" local="3499820320" remote="318763443893179392" Dst="-1" /><file name="Toronto.jpg" server="ftp.gfjourney.com/public_html/" local="3499820322" remote="318763443893179392" Dst="-1" /><file name="1000Islands.jpg" server="ftp.gfjourney.com/public_html/" local="3499820304" remote="318763443893179392" Dst="-1" /><file name="Niagara-FallsWinter.jpg" server="ftp.gfjourney.com/public_html/" local="3499820306" remote="318763443893179452" Dst="-1" /><file name="niagara-falls.jpg" server="ftp.gfjourney.com/public_html/" local="3499820306" remote="318763443893179452" Dst="-1" /><file name="St.House.jpg" server="ftp.gfjourney.com/public_html/" local="3499820320" remote="318763443893179452" Dst="-1" /><file name="Castle Toronto.jpg" server="ftp.gfjourney.com/public_html/" local="3499820304" remote="318763443893179452" Dst="-1" /><file name="church.jpg" server="ftp.gfjourney.com/public_html/" local="3499820306" remote="318763443893179452" Dst="-1" /><file name="ottawa.jpg" server="ftp.gfjourney.com/public_html/" local="3499820308" remote="318763443893179512" Dst="-1" /></dwsync>